phandler/__init__.py
phandler/phandler.py
phandler-1.6.dist-info/LICENSE
phandler-1.6.dist-info/METADATA
phandler-1.6.dist-info/WHEEL
phandler-1.6.dist-info/top_level.txt
phandler-1.6.dist-info/RECORD
