Metadata-Version: 2.1
Name: phandler
Version: 1.6
Summary: A package to fully control printing in Python. You can delete any line with just one command
Home-page: https://github.com/mategol/phandler-python
Author: Mateusz Gołembowski
Author-email: mateusz.golembowski.2002@gmail.com
License: UNKNOWN
Platform: UNKNOWN
Classifier: Programming Language :: Python :: 3
Classifier: License :: OSI Approved :: MIT License
Classifier: Operating System :: OS Independent
Requires-Python: >=3.6
License-File: LICENSE
